<?xml version="1.0" encoding="utf-8"?>
<TextureAtlas imagePath="gumball.png">
	<!-- Created with Adobe Animate version 22.0.2.168 -->
	<!-- http://www.adobe.com/products/animate.html -->
	<SubTexture name="Down0000" x="0" y="0" width="296" height="224" frameX="-2" frameY="-1" frameWidth="299" frameHeight="225"/>
	<SubTexture name="Down0001" x="296" y="0" width="299" height="223" frameX="0" frameY="-2" frameWidth="299" frameHeight="225"/>
	<SubTexture name="Down0002" x="595" y="0" width="207" height="219" frameX="-43" frameY="-1" frameWidth="299" frameHeight="225"/>
	<SubTexture name="Down0003" x="595" y="0" width="207" height="219" frameX="-43" frameY="-1" frameWidth="299" frameHeight="225"/>
	<SubTexture name="Down0004" x="802" y="0" width="210" height="220" frameX="-43" frameY="0" frameWidth="299" frameHeight="225"/>
	<SubTexture name="Down0005" x="802" y="0" width="210" height="220" frameX="-43" frameY="0" frameWidth="299" frameHeight="225"/>
	<SubTexture name="Down0006" x="1012" y="0" width="212" height="213" frameX="-41" frameY="-7" frameWidth="299" frameHeight="225"/>
	<SubTexture name="Down0007" x="1012" y="0" width="212" height="213" frameX="-41" frameY="-7" frameWidth="299" frameHeight="225"/>
	<SubTexture name="Down0008" x="1224" y="0" width="213" height="167" frameX="-41" frameY="-53" frameWidth="299" frameHeight="225"/>
	<SubTexture name="Down0009" x="1224" y="0" width="213" height="167" frameX="-41" frameY="-53" frameWidth="299" frameHeight="225"/>
	<SubTexture name="Down0010" x="1437" y="0" width="212" height="167" frameX="-41" frameY="-53" frameWidth="299" frameHeight="225"/>
	<SubTexture name="Down0011" x="1437" y="0" width="212" height="167" frameX="-41" frameY="-53" frameWidth="299" frameHeight="225"/>
	<SubTexture name="Down0012" x="1649" y="0" width="211" height="167" frameX="-42" frameY="-53" frameWidth="299" frameHeight="225"/>
	<SubTexture name="Down0013" x="1649" y="0" width="211" height="167" frameX="-42" frameY="-53" frameWidth="299" frameHeight="225"/>
	<SubTexture name="Idle0000" x="1860" y="0" width="138" height="197" frameX="-1" frameY="-2" frameWidth="139" frameHeight="199"/>
	<SubTexture name="Idle0001" x="1860" y="0" width="138" height="197" frameX="-1" frameY="-2" frameWidth="139" frameHeight="199"/>
	<SubTexture name="Idle0002" x="0" y="224" width="137" height="196" frameX="-1" frameY="-3" frameWidth="139" frameHeight="199"/>
	<SubTexture name="Idle0003" x="0" y="224" width="137" height="196" frameX="-1" frameY="-3" frameWidth="139" frameHeight="199"/>
	<SubTexture name="Idle0004" x="137" y="224" width="137" height="195" frameX="-1" frameY="-4" frameWidth="139" frameHeight="199"/>
	<SubTexture name="Idle0005" x="137" y="224" width="137" height="195" frameX="-1" frameY="-4" frameWidth="139" frameHeight="199"/>
	<SubTexture name="Idle0006" x="274" y="224" width="137" height="194" frameX="-1" frameY="-5" frameWidth="139" frameHeight="199"/>
	<SubTexture name="Idle0007" x="274" y="224" width="137" height="194" frameX="-1" frameY="-5" frameWidth="139" frameHeight="199"/>
	<SubTexture name="Idle0008" x="411" y="224" width="137" height="194" frameX="-1" frameY="-5" frameWidth="139" frameHeight="199"/>
	<SubTexture name="Idle0009" x="411" y="224" width="137" height="194" frameX="-1" frameY="-5" frameWidth="139" frameHeight="199"/>
	<SubTexture name="Idle0010" x="548" y="224" width="138" height="195" frameX="-1" frameY="-4" frameWidth="139" frameHeight="199"/>
	<SubTexture name="Idle0011" x="548" y="224" width="138" height="195" frameX="-1" frameY="-4" frameWidth="139" frameHeight="199"/>
	<SubTexture name="Idle0012" x="686" y="224" width="139" height="197" frameX="0" frameY="-2" frameWidth="139" frameHeight="199"/>
	<SubTexture name="Idle0013" x="686" y="224" width="139" height="197" frameX="0" frameY="-2" frameWidth="139" frameHeight="199"/>
	<SubTexture name="Idle0014" x="825" y="224" width="139" height="199"/>
	<SubTexture name="Idle0015" x="825" y="224" width="139" height="199"/>
	<SubTexture name="Laugh0000" x="964" y="224" width="156" height="208" frameX="-20" frameY="-17" frameWidth="180" frameHeight="241"/>
	<SubTexture name="Laugh0001" x="1120" y="224" width="147" height="206" frameX="-23" frameY="-19" frameWidth="180" frameHeight="241"/>
	<SubTexture name="Laugh0002" x="1267" y="224" width="146" height="205" frameX="-22" frameY="-20" frameWidth="180" frameHeight="241"/>
	<SubTexture name="Laugh0003" x="1413" y="224" width="146" height="205" frameX="-23" frameY="-20" frameWidth="180" frameHeight="241"/>
	<SubTexture name="Laugh0004" x="1559" y="224" width="148" height="208" frameX="-18" frameY="-17" frameWidth="180" frameHeight="241"/>
	<SubTexture name="Laugh0005" x="1707" y="224" width="146" height="209" frameX="-18" frameY="-16" frameWidth="180" frameHeight="241"/>
	<SubTexture name="Laugh0006" x="1853" y="224" width="147" height="216" frameX="-15" frameY="-9" frameWidth="180" frameHeight="241"/>
	<SubTexture name="Laugh0007" x="0" y="440" width="152" height="216" frameX="-14" frameY="-9" frameWidth="180" frameHeight="241"/>
	<SubTexture name="Laugh0008" x="152" y="440" width="158" height="211" frameX="-16" frameY="-14" frameWidth="180" frameHeight="241"/>
	<SubTexture name="Laugh0009" x="310" y="440" width="148" height="209" frameX="-17" frameY="-16" frameWidth="180" frameHeight="241"/>
	<SubTexture name="Laugh0010" x="458" y="440" width="161" height="230" frameX="-11" frameY="-4" frameWidth="180" frameHeight="241"/>
	<SubTexture name="Laugh0011" x="619" y="440" width="180" height="241"/>
	<SubTexture name="Laugh0012" x="799" y="440" width="178" height="237" frameX="-2" frameY="-4" frameWidth="180" frameHeight="241"/>
	<SubTexture name="Laugh0013" x="977" y="440" width="151" height="208" frameX="-19" frameY="-17" frameWidth="180" frameHeight="241"/>
	<SubTexture name="Laugh0014" x="1128" y="440" width="149" height="213" frameX="-15" frameY="-12" frameWidth="180" frameHeight="241"/>
	<SubTexture name="Laugh0015" x="1277" y="440" width="149" height="212" frameX="-14" frameY="-13" frameWidth="180" frameHeight="241"/>
	<SubTexture name="Laugh0016" x="1426" y="440" width="149" height="208" frameX="-14" frameY="-17" frameWidth="180" frameHeight="241"/>
	<SubTexture name="Laugh0017" x="1575" y="440" width="149" height="208" frameX="-14" frameY="-17" frameWidth="180" frameHeight="241"/>
	<SubTexture name="Laugh0018" x="1724" y="440" width="151" height="215" frameX="-10" frameY="-10" frameWidth="180" frameHeight="241"/>
	<SubTexture name="Laugh0019" x="1875" y="440" width="151" height="213" frameX="-10" frameY="-12" frameWidth="180" frameHeight="241"/>
	<SubTexture name="Laugh0020" x="0" y="681" width="149" height="210" frameX="-13" frameY="-15" frameWidth="180" frameHeight="241"/>
	<SubTexture name="Laugh0021" x="149" y="681" width="149" height="208" frameX="-14" frameY="-17" frameWidth="180" frameHeight="241"/>
	<SubTexture name="Laugh0022" x="298" y="681" width="151" height="212" frameX="-11" frameY="-13" frameWidth="180" frameHeight="241"/>
	<SubTexture name="Laugh0023" x="449" y="681" width="153" height="215" frameX="-8" frameY="-9" frameWidth="180" frameHeight="241"/>
	<SubTexture name="Laugh0024" x="602" y="681" width="151" height="214" frameX="-11" frameY="-11" frameWidth="180" frameHeight="241"/>
	<SubTexture name="Laugh0025" x="753" y="681" width="149" height="213" frameX="-13" frameY="-12" frameWidth="180" frameHeight="241"/>
	<SubTexture name="Laugh0026" x="902" y="681" width="148" height="213" frameX="-15" frameY="-14" frameWidth="180" frameHeight="241"/>
	<SubTexture name="Laugh0027" x="1050" y="681" width="149" height="212" frameX="-15" frameY="-15" frameWidth="180" frameHeight="241"/>
	<SubTexture name="Laugh0028" x="1199" y="681" width="149" height="209" frameX="-15" frameY="-16" frameWidth="180" frameHeight="241"/>
	<SubTexture name="Laugh0029" x="1348" y="681" width="148" height="208" frameX="-16" frameY="-17" frameWidth="180" frameHeight="241"/>
	<SubTexture name="Laugh0030" x="1496" y="681" width="148" height="208" frameX="-16" frameY="-17" frameWidth="180" frameHeight="241"/>
	<SubTexture name="Laugh0031" x="1644" y="681" width="148" height="208" frameX="-16" frameY="-17" frameWidth="180" frameHeight="241"/>
	<SubTexture name="Laugh0032" x="1792" y="681" width="148" height="208" frameX="-16" frameY="-17" frameWidth="180" frameHeight="241"/>
	<SubTexture name="Laugh0033" x="1792" y="681" width="148" height="208" frameX="-16" frameY="-17" frameWidth="180" frameHeight="241"/>
	<SubTexture name="Laugh0034" x="0" y="896" width="148" height="208" frameX="-16" frameY="-17" frameWidth="180" frameHeight="241"/>
	<SubTexture name="Laugh0035" x="0" y="896" width="148" height="208" frameX="-16" frameY="-17" frameWidth="180" frameHeight="241"/>
	<SubTexture name="Laugh0036" x="148" y="896" width="148" height="209" frameX="-16" frameY="-17" frameWidth="180" frameHeight="241"/>
	<SubTexture name="Laugh0037" x="148" y="896" width="148" height="209" frameX="-16" frameY="-17" frameWidth="180" frameHeight="241"/>
	<SubTexture name="Left0000" x="296" y="896" width="313" height="180" frameX="0" frameY="0" frameWidth="313" frameHeight="181"/>
	<SubTexture name="Left0001" x="609" y="896" width="311" height="178" frameX="0" frameY="-2" frameWidth="313" frameHeight="181"/>
	<SubTexture name="Left0002" x="920" y="896" width="200" height="167" frameX="-52" frameY="-7" frameWidth="313" frameHeight="181"/>
	<SubTexture name="Left0003" x="920" y="896" width="200" height="167" frameX="-52" frameY="-7" frameWidth="313" frameHeight="181"/>
	<SubTexture name="Left0004" x="1120" y="896" width="192" height="166" frameX="-57" frameY="-8" frameWidth="313" frameHeight="181"/>
	<SubTexture name="Left0005" x="1120" y="896" width="192" height="166" frameX="-57" frameY="-8" frameWidth="313" frameHeight="181"/>
	<SubTexture name="Left0006" x="1312" y="896" width="185" height="168" frameX="-61" frameY="-6" frameWidth="313" frameHeight="181"/>
	<SubTexture name="Left0007" x="1312" y="896" width="185" height="168" frameX="-61" frameY="-6" frameWidth="313" frameHeight="181"/>
	<SubTexture name="Left0008" x="1497" y="896" width="179" height="169" frameX="-62" frameY="-5" frameWidth="313" frameHeight="181"/>
	<SubTexture name="Left0009" x="1497" y="896" width="179" height="169" frameX="-62" frameY="-5" frameWidth="313" frameHeight="181"/>
	<SubTexture name="Left0010" x="1676" y="896" width="176" height="178" frameX="-65" frameY="-3" frameWidth="313" frameHeight="181"/>
	<SubTexture name="Left0011" x="1676" y="896" width="176" height="178" frameX="-65" frameY="-3" frameWidth="313" frameHeight="181"/>
	<SubTexture name="Left0012" x="1852" y="896" width="174" height="176" frameX="-67" frameY="-2" frameWidth="313" frameHeight="181"/>
	<SubTexture name="Left0013" x="1852" y="896" width="174" height="176" frameX="-67" frameY="-2" frameWidth="313" frameHeight="181"/>
	<SubTexture name="Right0000" x="0" y="1105" width="337" height="161" frameX="0" frameY="-11" frameWidth="344" frameHeight="176"/>
	<SubTexture name="Right0001" x="337" y="1105" width="344" height="160" frameX="0" frameY="-12" frameWidth="344" frameHeight="176"/>
	<SubTexture name="Right0002" x="681" y="1105" width="246" height="148" frameX="-48" frameY="-18" frameWidth="344" frameHeight="176"/>
	<SubTexture name="Right0003" x="681" y="1105" width="246" height="148" frameX="-48" frameY="-18" frameWidth="344" frameHeight="176"/>
	<SubTexture name="Right0004" x="927" y="1105" width="249" height="155" frameX="-48" frameY="-15" frameWidth="344" frameHeight="176"/>
	<SubTexture name="Right0005" x="927" y="1105" width="249" height="155" frameX="-48" frameY="-15" frameWidth="344" frameHeight="176"/>
	<SubTexture name="Right0006" x="1176" y="1105" width="235" height="159" frameX="-48" frameY="-7" frameWidth="344" frameHeight="176"/>
	<SubTexture name="Right0007" x="1176" y="1105" width="235" height="159" frameX="-48" frameY="-7" frameWidth="344" frameHeight="176"/>
	<SubTexture name="Right0008" x="1411" y="1105" width="221" height="175" frameX="-48" frameY="-1" frameWidth="344" frameHeight="176"/>
	<SubTexture name="Right0009" x="1411" y="1105" width="221" height="175" frameX="-48" frameY="-1" frameWidth="344" frameHeight="176"/>
	<SubTexture name="Right0010" x="1632" y="1105" width="210" height="174" frameX="-48" frameY="-1" frameWidth="344" frameHeight="176"/>
	<SubTexture name="Right0011" x="1632" y="1105" width="210" height="174" frameX="-48" frameY="-1" frameWidth="344" frameHeight="176"/>
	<SubTexture name="Right0012" x="0" y="1280" width="211" height="175" frameX="-48" frameY="0" frameWidth="344" frameHeight="176"/>
	<SubTexture name="Right0013" x="0" y="1280" width="211" height="175" frameX="-48" frameY="0" frameWidth="344" frameHeight="176"/>
	<SubTexture name="Up0000" x="211" y="1280" width="233" height="238" frameX="0" frameY="-1" frameWidth="233" frameHeight="239"/>
	<SubTexture name="Up0001" x="444" y="1280" width="172" height="238" frameX="-30" frameY="0" frameWidth="233" frameHeight="239"/>
	<SubTexture name="Up0002" x="616" y="1280" width="137" height="224" frameX="-43" frameY="-9" frameWidth="233" frameHeight="239"/>
	<SubTexture name="Up0003" x="616" y="1280" width="137" height="224" frameX="-43" frameY="-9" frameWidth="233" frameHeight="239"/>
	<SubTexture name="Up0004" x="753" y="1280" width="133" height="220" frameX="-47" frameY="-13" frameWidth="233" frameHeight="239"/>
	<SubTexture name="Up0005" x="753" y="1280" width="133" height="220" frameX="-47" frameY="-13" frameWidth="233" frameHeight="239"/>
	<SubTexture name="Up0006" x="886" y="1280" width="133" height="219" frameX="-52" frameY="-14" frameWidth="233" frameHeight="239"/>
	<SubTexture name="Up0007" x="886" y="1280" width="133" height="219" frameX="-52" frameY="-14" frameWidth="233" frameHeight="239"/>
	<SubTexture name="Up0008" x="1019" y="1280" width="133" height="218" frameX="-54" frameY="-15" frameWidth="233" frameHeight="239"/>
	<SubTexture name="Up0009" x="1019" y="1280" width="133" height="218" frameX="-54" frameY="-15" frameWidth="233" frameHeight="239"/>
	<SubTexture name="Up0010" x="1152" y="1280" width="133" height="218" frameX="-55" frameY="-15" frameWidth="233" frameHeight="239"/>
	<SubTexture name="Up0011" x="1152" y="1280" width="133" height="218" frameX="-55" frameY="-15" frameWidth="233" frameHeight="239"/>
	<SubTexture name="Up0012" x="1285" y="1280" width="133" height="218" frameX="-56" frameY="-15" frameWidth="233" frameHeight="239"/>
	<SubTexture name="Up0013" x="1285" y="1280" width="133" height="218" frameX="-56" frameY="-15" frameWidth="233" frameHeight="239"/>
</TextureAtlas>
